gnsscal.py
gnsscal-1.1.2.dist-info/LICENSE
gnsscal-1.1.2.dist-info/METADATA
gnsscal-1.1.2.dist-info/WHEEL
gnsscal-1.1.2.dist-info/top_level.txt
gnsscal-1.1.2.dist-info/RECORD
