Metadata-Version: 2.1
Name: gnsscal
Version: 1.1.2
Summary: Switch Gregorian date to GNSS calendar (GPS & BDS).
Home-page: https://github.com/purpleskyfall/gnsscal
Author: Jon Jiang
Author-email: jiangyingming@live.com
License: BSD
Platform: UNKNOWN
Classifier: Development Status :: 4 - Beta
Classifier: Intended Audience :: Science/Research
Classifier: Operating System :: OS Independent
Classifier: License :: OSI Approved :: BSD License
Classifier: Topic :: Scientific/Engineering
Classifier: Programming Language :: Python
